[{"display_name": "Jakarta, Gambir, Jakarta Pusat, Daerah Khusus Ibukota Jakarta, Indonesia", "importance": 0.87443870405128, "place_id": "153215", "lon": "106.827183", "geojson": {"type": "Point", "coordinates": [106.827183, -6.1753941]}, "lat": "-6.1753941", "osm_type": "node", "licence": "Data \u00a9 OpenStreetMap contributors, ODbL 1.0. http://www.openstreetmap.org/copyright", "osm_id": "29939632", "boundingbox": ["-6.3353941", "-6.0153941", "106.667183", "106.987183"], "type": "city", "class": "place", "icon": "https://nominatim.openstreetmap.org/images/mapicons/poi_place_city.p.20.png"}]